ezprez/__init__.py
ezprez/components.py
ezprez/core.py
ezprez-0.1.1.dist-info/LICENSE
ezprez-0.1.1.dist-info/METADATA
ezprez-0.1.1.dist-info/WHEEL
ezprez-0.1.1.dist-info/top_level.txt
ezprez-0.1.1.dist-info/RECORD
