Metadata-Version: 2.1
Name: ezprez
Version: 0.1.1
Summary: An object based api for generating web presentations/slideshows
Home-page: UNKNOWN
Author: Kieran Wood
Author-email: kieran@canadiancoding.ca
License: UNKNOWN
Project-URL: User Docs, https://ezprez.readthedocs.io
Project-URL: API Docs, https://kieranwood.ca/ezprez
Project-URL: Source, https://github.com/Descent098/ezprez
Project-URL: Bug Report, https://github.com/Descent098/ezprez/issues/new?assignees=Descent098&labels=bug&template=bug_report.md&title=%5BBUG%5D
Project-URL: Feature Request, https://github.com/Descent098/ezprez/issues/new?labels=enhancement&template=feature_request.md&title=%5BFeature%5D
Project-URL: Roadmap, https://github.com/Descent098/ezprez/projects
Platform: UNKNOWN
Classifier: Programming Language :: Python :: 3
Classifier: Operating System :: OS Independent
Classifier: Development Status :: 4 - Beta
Requires-Dist: pystall
Requires-Dist: elevate
Requires-Dist: tqdm
Provides-Extra: dev
Requires-Dist: pytest ; extra == 'dev'
Requires-Dist: mkdocs ; extra == 'dev'
